{
  "fetched_at_utc": "2026-03-30 09:40:22",
  "rates": [
    {
      "pair": "USD/EUR",
      "base": "USD",
      "target": "EUR",
      "mastercard_rate": 0.869489,
      "market_rate": 0.8701000213623047,
      "diff": -0.0006110213623047311,
      "opportunity": true,
      "error": null
    },
    {
      "pair": "EUR/USD",
      "base": "EUR",
      "target": "USD",
      "mastercard_rate": 1.1559999,
      "market_rate": 1.1492931842803955,
      "diff": 0.006706715719604572,
      "opportunity": false,
      "error": null
    },
    {
      "pair": "USD/CAD",
      "base": "USD",
      "target": "CAD",
      "mastercard_rate": 1.3884,
      "market_rate": 1.3910000324249268,
      "diff": -0.0026000324249266793,
      "opportunity": true,
      "error": null
    },
    {
      "pair": "CAD/USD",
      "base": "CAD",
      "target": "USD",
      "mastercard_rate": 0.7228045,
      "market_rate": 0.7189072370529175,
      "diff": 0.0038972629470824804,
      "opportunity": false,
      "error": null
    },
    {
      "pair": "USD/MXN",
      "base": "USD",
      "target": "MXN",
      "mastercard_rate": 18.0667,
      "market_rate": 18.083999633789062,
      "diff": -0.01729963378906163,
      "opportunity": true,
      "error": null
    },
    {
      "pair": "MXN/USD",
      "base": "MXN",
      "target": "USD",
      "mastercard_rate": 0.0562734,
      "market_rate": 0.055297501385211945,
      "diff": 0.0009758986147880566,
      "opportunity": false,
      "error": null
    },
    {
      "pair": "USD/JPY",
      "base": "USD",
      "target": "JPY",
      "mastercard_rate": 160.2,
      "market_rate": 159.66299438476562,
      "diff": 0.5370056152343636,
      "opportunity": false,
      "error": null
    },
    {
      "pair": "JPY/USD",
      "base": "JPY",
      "target": "USD",
      "mastercard_rate": 0.0062747,
      "market_rate": 0.006263192277401686,
      "diff": 1.1507722598314528e-05,
      "opportunity": false,
      "error": null
    },
    {
      "pair": "USD/GBP",
      "base": "USD",
      "target": "GBP",
      "mastercard_rate": 0.753636,
      "market_rate": 0.7555270195007324,
      "diff": -0.0018910195007324493,
      "opportunity": true,
      "error": null
    },
    {
      "pair": "GBP/USD",
      "base": "GBP",
      "target": "USD",
      "mastercard_rate": 1.3372989,
      "market_rate": 1.3235794305801392,
      "diff": 0.013719469419860797,
      "opportunity": false,
      "error": null
    },
    {
      "pair": "EUR/GBP",
      "base": "EUR",
      "target": "GBP",
      "mastercard_rate": 0.8678,
      "market_rate": 0.8680599927902222,
      "diff": -0.00025999279022215216,
      "opportunity": true,
      "error": null
    },
    {
      "pair": "GBP/EUR",
      "base": "GBP",
      "target": "EUR",
      "mastercard_rate": 1.1572735,
      "market_rate": 1.1519360542297363,
      "diff": 0.005337445770263738,
      "opportunity": false,
      "error": null
    }
  ]
}