{
  "fetched_at_utc": "2026-03-31 08:20:29",
  "rates": [
    {
      "pair": "USD/EUR",
      "base": "USD",
      "target": "EUR",
      "mastercard_rate": 0.873973,
      "market_rate": 0.871999979019165,
      "diff": 0.001973020980834961,
      "opportunity": false,
      "error": null
    },
    {
      "pair": "EUR/USD",
      "base": "EUR",
      "target": "USD",
      "mastercard_rate": 1.1529996,
      "market_rate": 1.1467890739440918,
      "diff": 0.0062105260559082165,
      "opportunity": false,
      "error": null
    },
    {
      "pair": "USD/CAD",
      "base": "USD",
      "target": "CAD",
      "mastercard_rate": 1.3948,
      "market_rate": 1.3939299583435059,
      "diff": 0.0008700416564941804,
      "opportunity": false,
      "error": null
    },
    {
      "pair": "CAD/USD",
      "base": "CAD",
      "target": "USD",
      "mastercard_rate": 0.7220217,
      "market_rate": 0.7173961400985718,
      "diff": 0.004625559901428211,
      "opportunity": false,
      "error": null
    },
    {
      "pair": "USD/MXN",
      "base": "USD",
      "target": "MXN",
      "mastercard_rate": 18.0667,
      "market_rate": 18.07954978942871,
      "diff": -0.012849789428710068,
      "opportunity": true,
      "error": null
    },
    {
      "pair": "MXN/USD",
      "base": "MXN",
      "target": "USD",
      "mastercard_rate": 0.0554327,
      "market_rate": 0.05532228201627731,
      "diff": 0.00011041798372268818,
      "opportunity": false,
      "error": null
    },
    {
      "pair": "USD/JPY",
      "base": "USD",
      "target": "JPY",
      "mastercard_rate": 160.5,
      "market_rate": 159.62399291992188,
      "diff": 0.876007080078125,
      "opportunity": false,
      "error": null
    },
    {
      "pair": "JPY/USD",
      "base": "JPY",
      "target": "USD",
      "mastercard_rate": 0.0062775,
      "market_rate": 0.006264722440391779,
      "diff": 1.2777559608221148e-05,
      "opportunity": false,
      "error": null
    },
    {
      "pair": "USD/GBP",
      "base": "USD",
      "target": "GBP",
      "mastercard_rate": 0.759301,
      "market_rate": 0.7573069930076599,
      "diff": 0.0019940069923400916,
      "opportunity": false,
      "error": null
    },
    {
      "pair": "GBP/USD",
      "base": "GBP",
      "target": "USD",
      "mastercard_rate": 1.3288984,
      "market_rate": 1.3204684257507324,
      "diff": 0.008429974249267502,
      "opportunity": false,
      "error": null
    },
    {
      "pair": "EUR/GBP",
      "base": "EUR",
      "target": "GBP",
      "mastercard_rate": 0.87,
      "market_rate": 0.8682000041007996,
      "diff": 0.001799995899200435,
      "opportunity": false,
      "error": null
    },
    {
      "pair": "GBP/EUR",
      "base": "GBP",
      "target": "EUR",
      "mastercard_rate": 1.1540681,
      "market_rate": 1.1517640352249146,
      "diff": 0.0023040647750853793,
      "opportunity": false,
      "error": null
    }
  ]
}