{
  "fetched_at_utc": "2026-03-30 05:40:25",
  "rates": [
    {
      "pair": "USD/EUR",
      "base": "USD",
      "target": "EUR",
      "mastercard_rate": 0.869489,
      "market_rate": 0.8684999942779541,
      "diff": 0.0009890057220458548,
      "opportunity": false,
      "error": null
    },
    {
      "pair": "EUR/USD",
      "base": "EUR",
      "target": "USD",
      "mastercard_rate": 1.1559999,
      "market_rate": 1.151410460472107,
      "diff": 0.004589439527893147,
      "opportunity": false,
      "error": null
    },
    {
      "pair": "USD/CAD",
      "base": "USD",
      "target": "CAD",
      "mastercard_rate": 1.3884,
      "market_rate": 1.3892600536346436,
      "diff": -0.0008600536346434762,
      "opportunity": true,
      "error": null
    },
    {
      "pair": "CAD/USD",
      "base": "CAD",
      "target": "USD",
      "mastercard_rate": 0.7228045,
      "market_rate": 0.7198076248168945,
      "diff": 0.0029968751831054297,
      "opportunity": false,
      "error": null
    },
    {
      "pair": "USD/MXN",
      "base": "USD",
      "target": "MXN",
      "mastercard_rate": 18.0667,
      "market_rate": 18.073999404907227,
      "diff": -0.007299404907225693,
      "opportunity": true,
      "error": null
    },
    {
      "pair": "MXN/USD",
      "base": "MXN",
      "target": "USD",
      "mastercard_rate": 0.0562734,
      "market_rate": 0.05532809719443321,
      "diff": 0.0009453028055667889,
      "opportunity": false,
      "error": null
    },
    {
      "pair": "USD/JPY",
      "base": "USD",
      "target": "JPY",
      "mastercard_rate": 160.2,
      "market_rate": 159.76600646972656,
      "diff": 0.43399353027342613,
      "opportunity": false,
      "error": null
    },
    {
      "pair": "JPY/USD",
      "base": "JPY",
      "target": "USD",
      "mastercard_rate": 0.0062747,
      "market_rate": 0.006259153597056866,
      "diff": 1.554640294313455e-05,
      "opportunity": false,
      "error": null
    },
    {
      "pair": "USD/GBP",
      "base": "USD",
      "target": "GBP",
      "mastercard_rate": 0.753636,
      "market_rate": 0.7535439729690552,
      "diff": 9.20270309447968e-05,
      "opportunity": false,
      "error": null
    },
    {
      "pair": "GBP/USD",
      "base": "GBP",
      "target": "USD",
      "mastercard_rate": 1.3372989,
      "market_rate": 1.3270626068115234,
      "diff": 0.01023629318847652,
      "opportunity": false,
      "error": null
    },
    {
      "pair": "EUR/GBP",
      "base": "EUR",
      "target": "GBP",
      "mastercard_rate": 0.8678,
      "market_rate": 0.8672900199890137,
      "diff": 0.0005099800109863439,
      "opportunity": false,
      "error": null
    },
    {
      "pair": "GBP/EUR",
      "base": "GBP",
      "target": "EUR",
      "mastercard_rate": 1.1572735,
      "market_rate": 1.1529099941253662,
      "diff": 0.004363505874633855,
      "opportunity": false,
      "error": null
    }
  ]
}