{
  "fetched_at_utc": "2026-03-26 23:20:23",
  "rates": [
    {
      "pair": "USD/EUR",
      "base": "USD",
      "target": "EUR",
      "mastercard_rate": 0.86798,
      "market_rate": 0.8664000034332275,
      "diff": 0.0015799965667724347,
      "opportunity": false,
      "error": null
    },
    {
      "pair": "EUR/USD",
      "base": "EUR",
      "target": "USD",
      "mastercard_rate": 1.1584989,
      "market_rate": 1.1542012691497803,
      "diff": 0.004297630850219836,
      "opportunity": false,
      "error": null
    },
    {
      "pair": "USD/CAD",
      "base": "USD",
      "target": "CAD",
      "mastercard_rate": 1.386,
      "market_rate": 1.3849899768829346,
      "diff": 0.0010100231170653284,
      "opportunity": false,
      "error": null
    },
    {
      "pair": "CAD/USD",
      "base": "CAD",
      "target": "USD",
      "mastercard_rate": 0.7249529,
      "market_rate": 0.7220268845558167,
      "diff": 0.002926015444183361,
      "opportunity": false,
      "error": null
    },
    {
      "pair": "USD/MXN",
      "base": "USD",
      "target": "MXN",
      "mastercard_rate": 17.7548,
      "market_rate": 17.909000396728516,
      "diff": -0.15420039672851615,
      "opportunity": true,
      "error": null
    },
    {
      "pair": "MXN/USD",
      "base": "MXN",
      "target": "USD",
      "mastercard_rate": 0.0564487,
      "market_rate": 0.05583784729242325,
      "diff": 0.0006108527075767492,
      "opportunity": false,
      "error": null
    },
    {
      "pair": "USD/JPY",
      "base": "USD",
      "target": "JPY",
      "mastercard_rate": 159.72,
      "market_rate": 159.6540069580078,
      "diff": 0.06599304199218636,
      "opportunity": false,
      "error": null
    },
    {
      "pair": "JPY/USD",
      "base": "JPY",
      "target": "USD",
      "mastercard_rate": 0.0062854,
      "market_rate": 0.006263544782996178,
      "diff": 2.185521700382234e-05,
      "opportunity": false,
      "error": null
    },
    {
      "pair": "USD/GBP",
      "base": "USD",
      "target": "GBP",
      "mastercard_rate": 0.750807,
      "market_rate": 0.7497479915618896,
      "diff": 0.0010590084381103537,
      "opportunity": false,
      "error": null
    },
    {
      "pair": "GBP/USD",
      "base": "GBP",
      "target": "USD",
      "mastercard_rate": 1.3394986,
      "market_rate": 1.3337814807891846,
      "diff": 0.005717119210815413,
      "opportunity": false,
      "error": null
    },
    {
      "pair": "EUR/GBP",
      "base": "EUR",
      "target": "GBP",
      "mastercard_rate": 0.8665,
      "market_rate": 0.8650199770927429,
      "diff": 0.001480022907257128,
      "opportunity": false,
      "error": null
    },
    {
      "pair": "GBP/EUR",
      "base": "GBP",
      "target": "EUR",
      "mastercard_rate": 1.1580776,
      "market_rate": 1.1559549570083618,
      "diff": 0.002122642991638113,
      "opportunity": false,
      "error": null
    }
  ]
}