{
  "fetched_at_utc": "2026-03-27 17:00:27",
  "rates": [
    {
      "pair": "USD/EUR",
      "base": "USD",
      "target": "EUR",
      "mastercard_rate": 0.86798,
      "market_rate": 0.8677999973297119,
      "diff": 0.00018000267028805972,
      "opportunity": false,
      "error": null
    },
    {
      "pair": "EUR/USD",
      "base": "EUR",
      "target": "USD",
      "mastercard_rate": 1.1584989,
      "market_rate": 1.152339220046997,
      "diff": 0.006159679953003039,
      "opportunity": false,
      "error": null
    },
    {
      "pair": "USD/CAD",
      "base": "USD",
      "target": "CAD",
      "mastercard_rate": 1.386,
      "market_rate": 1.3881100416183472,
      "diff": -0.0021100416183472692,
      "opportunity": true,
      "error": null
    },
    {
      "pair": "CAD/USD",
      "base": "CAD",
      "target": "USD",
      "mastercard_rate": 0.7249529,
      "market_rate": 0.7204039692878723,
      "diff": 0.004548930712127697,
      "opportunity": false,
      "error": null
    },
    {
      "pair": "USD/MXN",
      "base": "USD",
      "target": "MXN",
      "mastercard_rate": 17.7548,
      "market_rate": 18.042999267578125,
      "diff": -0.28819926757812553,
      "opportunity": true,
      "error": null
    },
    {
      "pair": "MXN/USD",
      "base": "MXN",
      "target": "USD",
      "mastercard_rate": 0.0564487,
      "market_rate": 0.05542315915226936,
      "diff": 0.001025540847730634,
      "opportunity": false,
      "error": null
    },
    {
      "pair": "USD/JPY",
      "base": "USD",
      "target": "JPY",
      "mastercard_rate": 159.72,
      "market_rate": 160.14500427246094,
      "diff": -0.42500427246093864,
      "opportunity": true,
      "error": null
    },
    {
      "pair": "JPY/USD",
      "base": "JPY",
      "target": "USD",
      "mastercard_rate": 0.0062854,
      "market_rate": 0.0062443409115076065,
      "diff": 4.105908849239351e-05,
      "opportunity": false,
      "error": null
    },
    {
      "pair": "USD/GBP",
      "base": "USD",
      "target": "GBP",
      "mastercard_rate": 0.750807,
      "market_rate": 0.7532309889793396,
      "diff": -0.0024239889793395974,
      "opportunity": true,
      "error": null
    },
    {
      "pair": "GBP/USD",
      "base": "GBP",
      "target": "USD",
      "mastercard_rate": 1.3394986,
      "market_rate": 1.3276139497756958,
      "diff": 0.011884650224304183,
      "opportunity": false,
      "error": null
    },
    {
      "pair": "EUR/GBP",
      "base": "EUR",
      "target": "GBP",
      "mastercard_rate": 0.8665,
      "market_rate": 0.867579996585846,
      "diff": -0.0010799965858458993,
      "opportunity": true,
      "error": null
    },
    {
      "pair": "GBP/EUR",
      "base": "GBP",
      "target": "EUR",
      "mastercard_rate": 1.1580776,
      "market_rate": 1.1526039838790894,
      "diff": 0.005473616120910574,
      "opportunity": false,
      "error": null
    }
  ]
}